loone_data_prep/GEOGLOWS_LOONE_DATA_PREP.py
loone_data_prep/LOONE_DATA_PREP.py
loone_data_prep/__init__.py
loone_data_prep/data_analyses_fns.py
loone_data_prep/herbie_utils.py
loone_data_prep/utils.py
loone_data_prep/flow_data/S65E_total.py
loone_data_prep/flow_data/__init__.py
loone_data_prep/flow_data/forecast_bias_correction.py
loone_data_prep/flow_data/get_forecast_flows.py
loone_data_prep/flow_data/get_inflows.py
loone_data_prep/flow_data/get_outflows.py
loone_data_prep/flow_data/hydro.py
loone_data_prep/forecast_scripts/Chla_merged.py
loone_data_prep/forecast_scripts/forecast_stages.py
loone_data_prep/forecast_scripts/get_Chla_predicted.py
loone_data_prep/forecast_scripts/get_NO_Loads_predicted.py
loone_data_prep/forecast_scripts/loone_q_predict.py
loone_data_prep/forecast_scripts/loone_wq_predict.py
loone_data_prep/forecast_scripts/new_combined_weather_forecast.py
loone_data_prep/forecast_scripts/predict_PI.py
loone_data_prep/forecast_scripts/trib_cond.py
loone_data_prep/water_level_data/__init__.py
loone_data_prep/water_level_data/get_all.py
loone_data_prep/water_level_data/hydro.py
loone_data_prep/water_quality_data/__init__.py
loone_data_prep/water_quality_data/get_inflows.py
loone_data_prep/water_quality_data/get_lake_wq.py
loone_data_prep/water_quality_data/wq.py
loone_data_prep/weather_data/__init__.py
loone_data_prep/weather_data/get_all.py
loone_data_prep/weather_data/weather.py
loone_data_prep-1.3.0.dist-info/licenses/LICENSE
loone_data_prep-1.3.0.dist-info/METADATA
loone_data_prep-1.3.0.dist-info/WHEEL
loone_data_prep-1.3.0.dist-info/top_level.txt
loone_data_prep-1.3.0.dist-info/RECORD
