Metadata-Version: 2.4
Name: loone_data_prep
Version: 1.3.0
Summary: Prepare data to run the LOONE model.
Author-email: Osama Tarabih <osamatarabih@usf.edu>
Maintainer-email: Michael Souffront <msouffront@aquaveo.com>, James Dolinar <jdolinar@aquaveo.com>
License: BSD-3-Clause License
License-File: LICENSE
Requires-Dist: rpy2
Requires-Dist: retry
Requires-Dist: numpy<2
Requires-Dist: pandas
Requires-Dist: scipy
Requires-Dist: geoglows>=2.0.0
Requires-Dist: herbie-data[extras]==2025.5.0
Requires-Dist: openmeteo_requests
Requires-Dist: requests_cache
Requires-Dist: retry-requests
Requires-Dist: eccodes==2.41.0
Requires-Dist: xarray==2025.4.0
Dynamic: license-file
